vlm/__init__.py
vlm/airfoils.py
vlm/geometry.py
vlm/mesh_generator.py
vlm/panel.py
vlm/vlm.py
vlm/vortices.py
vlm-0.0.1.dist-info/COPYING
vlm-0.0.1.dist-info/METADATA
vlm-0.0.1.dist-info/WHEEL
vlm-0.0.1.dist-info/top_level.txt
vlm-0.0.1.dist-info/RECORD
