Metadata-Version: 2.1
Name: vlm
Version: 0.0.1
Summary: Python Vortex Lattice Method
Home-page: https://github.com/aqreed/PyVLM
Author: aqreed
License: UNKNOWN
Platform: UNKNOWN
Requires-Dist: numpy
Requires-Dist: matplotlib
